[{"stratum":"default","age":"00-04","geography":"England","geography_type":"Nation","geography_code":"E92000001","period_start":"2023-08-28","period_end":"2023-09-04","metric_value":0,"parent_theme":"infectious_disease","child_theme":"respiratory","topic":"Influenza","metric_group":"headline","sex":"all","metric":"influenza_headline_ICUHDUadmissionRateChange","refresh_date":"2023-09-14"},{"stratum":"default","age":"05-14","geography":"England","geography_type":"Nation","geography_code":"E92000001","period_start":"2023-08-28","period_end":"2023-09-04","metric_value":0,"parent_theme":"infectious_disease","child_theme":"respiratory","topic":"Influenza","metric_group":"headline","sex":"all","metric":"influenza_headline_ICUHDUadmissionRateChange","refresh_date":"2023-09-14"},{"stratum":"default","age":"15-44","geography":"England","geography_type":"Nation","geography_code":"E92000001","period_start":"2023-08-28","period_end":"2023-09-04","metric_value":0,"parent_theme":"infectious_disease","child_theme":"respiratory","topic":"Influenza","metric_group":"headline","sex":"all","metric":"influenza_headline_ICUHDUadmissionRateChange","refresh_date":"2023-09-14"},{"stratum":"default","age":"45-54","geography":"England","geography_type":"Nation","geography_code":"E92000001","period_start":"2023-08-28","period_end":"2023-09-04","metric_value":0.02,"parent_theme":"infectious_disease","child_theme":"respiratory","topic":"Influenza","metric_group":"headline","sex":"all","metric":"influenza_headline_ICUHDUadmissionRateChange","refresh_date":"2023-09-14"},{"stratum":"default","age":"55-64","geography":"England","geography_type":"Nation","geography_code":"E92000001","period_start":"2023-08-28","period_end":"2023-09-04","metric_value":-0.04,"parent_theme":"infectious_disease","child_theme":"respiratory","topic":"Influenza","metric_group":"headline","sex":"all","metric":"influenza_headline_ICUHDUadmissionRateChange","refresh_date":"2023-09-14"},{"stratum":"default","age":"65-74","geography":"England","geography_type":"Nation","geography_code":"E92000001","period_start":"2023-08-28","period_end":"2023-09-04","metric_value":0,"parent_theme":"infectious_disease","child_theme":"respiratory","topic":"Influenza","metric_group":"headline","sex":"all","metric":"influenza_headline_ICUHDUadmissionRateChange","refresh_date":"2023-09-14"},{"stratum":"default","age":"75-84","geography":"England","geography_type":"Nation","geography_code":"E92000001","period_start":"2023-08-28","period_end":"2023-09-04","metric_value":0.04,"parent_theme":"infectious_disease","child_theme":"respiratory","topic":"Influenza","metric_group":"headline","sex":"all","metric":"influenza_headline_ICUHDUadmissionRateChange","refresh_date":"2023-09-14"},{"stratum":"default","age":"85+","geography":"England","geography_type":"Nation","geography_code":"E92000001","period_start":"2023-08-28","period_end":"2023-09-04","metric_value":-0.1,"parent_theme":"infectious_disease","child_theme":"respiratory","topic":"Influenza","metric_group":"headline","sex":"all","metric":"influenza_headline_ICUHDUadmissionRateChange","refresh_date":"2023-09-14"},{"stratum":"default","age":"all","geography":"England","geography_type":"Nation","geography_code":"E92000001","period_start":"2023-08-28","period_end":"2023-09-04","metric_value":0,"parent_theme":"infectious_disease","child_theme":"respiratory","topic":"Influenza","metric_group":"headline","sex":"all","metric":"influenza_headline_ICUHDUadmissionRateChange","refresh_date":"2023-09-14"}]
